pyramid_jsonapi/__init__.py
pyramid_jsonapi/callbacks_doc.py
pyramid_jsonapi/collection_view.py
pyramid_jsonapi/endpoints.py
pyramid_jsonapi/filters.py
pyramid_jsonapi/http_query.py
pyramid_jsonapi/permissions.py
pyramid_jsonapi/resource.py
pyramid_jsonapi/unit_tests.py
pyramid_jsonapi/version.py
pyramid_jsonapi/metadata/__init__.py
pyramid_jsonapi/metadata/JSONSchema/__init__.py
pyramid_jsonapi/metadata/OpenAPI/__init__.py
pyramid_jsonapi/metadata/OpenAPI/swagger-ui/index.mako
pyramid_jsonapi/schema/jsonapi-schema.json
pyramid_jsonapi/workflow/__init__.py
pyramid_jsonapi/workflow/loop/__init__.py
pyramid_jsonapi/workflow/loop/collection_get.py
pyramid_jsonapi/workflow/loop/collection_post.py
pyramid_jsonapi/workflow/loop/item_delete.py
pyramid_jsonapi/workflow/loop/item_get.py
pyramid_jsonapi/workflow/loop/item_patch.py
pyramid_jsonapi/workflow/loop/related_get.py
pyramid_jsonapi/workflow/loop/relationships_delete.py
pyramid_jsonapi/workflow/loop/relationships_get.py
pyramid_jsonapi/workflow/loop/relationships_patch.py
pyramid_jsonapi/workflow/loop/relationships_post.py
pyramid_jsonapi-2.2.8.dist-info/LICENSE
pyramid_jsonapi-2.2.8.dist-info/METADATA
pyramid_jsonapi-2.2.8.dist-info/WHEEL
pyramid_jsonapi-2.2.8.dist-info/top_level.txt
pyramid_jsonapi-2.2.8.dist-info/RECORD
