Metadata-Version: 2.1
Name: pyramid-jsonapi
Version: 2.2.8
Summary: Auto-build JSON API from sqlalchemy models using the pyramid framework
Home-page: https://github.com/colinhiggs/pyramid-jsonapi
Author: Colin Higgs
Author-email: colin.higgs70@gmail.com
License: GNU Affero General Public License v3 or later (AGPLv3+)
Keywords: json,api,json-api,jsonapi,jsonschema,openapi,pyramid,sqlalchemy
Platform: UNKNOWN
Classifier: Development Status :: 5 - Production/Stable
Classifier: Framework :: Pyramid
Classifier: Intended Audience :: Developers
Classifier: License :: OSI Approved :: GNU Affero General Public License v3 or later (AGPLv3+)
Classifier: Programming Language :: Python :: 3
Classifier: Programming Language :: Python :: 3.4
Classifier: Programming Language :: Python :: 3.5
Classifier: Programming Language :: Python :: 3.6
Classifier: Topic :: Internet :: WWW/HTTP
Classifier: Topic :: Internet :: WWW/HTTP :: Dynamic Content
Classifier: Topic :: Software Development :: Libraries :: Application Frameworks
Classifier: Topic :: Software Development :: Libraries :: Python Modules
License-File: LICENSE
Requires-Dist: SQLAlchemy
Requires-Dist: alchemyjsonschema
Requires-Dist: jsonschema
Requires-Dist: pkginfo
Requires-Dist: pyramid
Requires-Dist: pyramid-mako
Requires-Dist: pyramid-settings-wrapper
Requires-Dist: pyyaml (>=5.1)
Requires-Dist: rqlalchemy
